YcthProgressbar/__init__.py
YcthProgressbar/model.py
YcthProgressbar-1.0.0.dist-info/METADATA
YcthProgressbar-1.0.0.dist-info/WHEEL
YcthProgressbar-1.0.0.dist-info/top_level.txt
YcthProgressbar-1.0.0.dist-info/RECORD
