Metadata-Version: 2.2
Name: YcthProgressbar
Version: 1.0.0
Summary: 一个具有高性能、主题切换和动画效果的PySide6自定义进度条组件
Home-page: https://github.com/ycth/YcthProgressbar
Author: Ycth
Author-email: 307639884@example.com
Keywords: pyside6,qt,progressbar,ui,widget,theme,animated,gradient
Classifier: Development Status :: 4 - Beta
Classifier: Intended Audience :: Developers
Classifier: License :: OSI Approved :: MIT License
Classifier: Programming Language :: Python :: 3.11
Classifier: Topic :: Software Development :: User Interfaces
Requires-Python: >=3.6
Requires-Dist: pyside6>=6.0.0
Dynamic: author
Dynamic: author-email
Dynamic: classifier
Dynamic: description
Dynamic: description-content-type
Dynamic: home-page
Dynamic: keywords
Dynamic: requires-dist
Dynamic: requires-python
Dynamic: summary
